{
  "pretrained_model_name_or_path": "F:/AI/Diffusers/stable-diffusion-v1-5",
  "pretrained_vae_name_or_path": null,
  "revision": "fp16",
  "tokenizer_name": null,
  "instance_data_dir": null,
  "class_data_dir": null,
  "instance_prompt": null,
  "class_prompt": null,
  "save_sample_prompt": "a bedroom,modern tardis style",
  "save_sample_negative_prompt": null,
  "n_save_sample": 4,
  "save_guidance_scale": 7.5,
  "save_infer_steps": 50,
  "pad_tokens": false,
  "with_prior_preservation": true,
  "prior_loss_weight": 1.0,
  "num_class_images": 100,
  "output_dir": "F:/AI/Outputs/Dreambooth/Tardisfusion",
  "seed": 42,
  "resolution": 512,
  "center_crop": false,
  "train_text_encoder": true,
  "train_batch_size": 1,
  "sample_batch_size": 8,
  "num_train_epochs": 9,
  "max_train_steps": 2500,
  "gradient_accumulation_steps": 1,
  "gradient_checkpointing": true,
  "learning_rate": 1e-06,
  "scale_lr": false,
  "lr_scheduler": "constant",
  "lr_warmup_steps": 0,
  "use_8bit_adam": false,
  "adam_beta1": 0.9,
  "adam_beta2": 0.999,
  "adam_weight_decay": 0.01,
  "adam_epsilon": 1e-08,
  "max_grad_norm": 1.0,
  "push_to_hub": false,
  "hub_token": null,
  "hub_model_id": null,
  "logging_dir": "logs",
  "log_interval": 10,
  "save_interval": 500,
  "save_min_steps": 0,
  "mixed_precision": "no",
  "not_cache_latents": false,
  "local_rank": -1,
  "concepts_list": [
    {
      "instance_prompt": "Classic Tardis style",
      "instance_data_dir": "F:/AI/Datasets/DrWho/ClassicTardis",
      "class_prompt": "black and white style",
      "class_data_dir": "F:/AI/Datasets/Regularisation/BlackNWhiteStyle"
    },
    {
      "instance_prompt": "Modern Tardis style",
      "instance_data_dir": "F:/AI/Datasets/DrWho/ModernTardis",
      "class_prompt": "strange style",
      "class_data_dir": "F:/AI/Datasets/Regularisation/StrangeStyle"
    },
    {
      "instance_prompt": "Tardis Box style",
      "instance_data_dir": "F:/AI/Datasets/DrWho/ExteriorTardis",
      "class_prompt": "a phonebooth",
      "class_data_dir": "F:/AI/Datasets/Regularisation/APhonebooth"
    }
  ]
}